{"title":"Insurance Branch Group","hideTitle":false,"id":"InsuranceBranchGroupPaging","addButton":false,"addLink":"","pathOption":"","backButton":false,"component":[{"customComponent":{"componentRef":"${VendorGroupPaging}"},"id":"b85f5258-2836-44a9-80bb-28ea6de42e4c"}],"serviceUrl":{"add":{"environment":"","apiPath":"","apiUrl":""},"edit":{"environment":"","apiPath":"","apiUrl":""},"createRfa":{"environment":"","apiPath":"","apiUrl":""}},"isRedirect":false,"redirectOption":"","redirectLink":"","hideSubmitButton":false,"hideCancelButton":false,"listBtn":[{"displayName":"Add","id":"addId","key":"","position":"top","icon":"ft-plus-circle","cssClass":"btn-primary-2","conditions":[],"btnType":"button","action":{"type":"link","path":"/Vendor/SelfCustom/Group/Add","target":"_self","params":[{"propName":"MrVendorCategoryCode","propValue":"MrVendorCategoryCode"}]}}],"onInit":[],"isOverrideSubmit":false,"onSubmit":[],"isOverrideCancel":false,"onCancel":{},"customToastrMsg":"","conditionalTitle":[{"title":"Insurance Branch Group","conditions":[]}]}