{"title":"Other Receive Approval Detail","hideTitle":false,"id":"OtherReceiveApprovalDetail","addButton":false,"addLink":"","pathOption":"","backButton":false,"component":[{"container":{"key":"OthTrxView","className":"OthTrxViewComponent","cssClass":"","input":{"OthTrxNo":"TransactionNo","IsTitle":"0"}},"id":"65265ef2-83fb-4894-8018-d31b00f46d0b"}],"serviceUrl":{"add":{"environment":"","apiPath":"","apiUrl":""},"edit":{"environment":"","apiPath":"","apiUrl":""},"createRfa":{"environment":"","apiPath":"","apiUrl":""}},"isRedirect":false,"redirectOption":"","redirectLink":"","hideSubmitButton":false,"listBtn":[]}