{"title":"Pdc Receive Inquiry","hideTitle":false,"id":"Pdcreceiveinquiry","addButton":false,"addLink":"","pathOption":"","backButton":false,"component":[{"paging":{"environment":"PDCUrl","apiVersion":"v1","uri":"http://r3app-server/PDC","pagingInput":{"title":"","sectionTitle":"","querystring":{"name":"searchPdcReceiveInquiry"},"exportExcel":false,"component":[{"id":"profficeCodeSearchId","type":"dropdown","label":"OFFICE NAME","name":"pr.OFFICE_CODE","value":"","placeholder":"","datatype":"text","isFromURL":true,"ddlType":"all","isEvent":false,"environment":"FOU","path":"/v1/RefOffice/GetListKvpActiveRefOfficeForPaging","criteriaPropName":"","criteriaPropValue":"","isQueryIn":false},{"id":"prreceiptNoSearchId","type":"textbox","label":"PDC RECEIPT NO","name":"pr.RECEIPT_NO","value":"","placeholder":"","datatype":"text"},{"id":"prrcvFromUsernameSearchId","type":"textbox","label":"RECEIVE FROM","name":"pr.RCV_FROM_USERNAME","value":"","placeholder":"","datatype":"text"},{"id":"prreceiptFormNoSearchId","type":"textbox","label":"RECEIPT FORM NO","name":"pr.RECEIPT_FORM_NO","value":"","placeholder":"","datatype":"text"},{"id":"prtotalPdcGroupAmtSearchId","type":"numeric","label":"TOTAL PDC AMOUNT >=","name":"pr.TOTAL_PDC_GROUP_AMT","value":"","placeholder":"","datatype":"numeric","restriction":"gte"},{"id":"prtotalPdcGroupAmtSearchId","type":"numeric","label":"TOTAL PDC AMOUNT <=","name":"pr.TOTAL_PDC_GROUP_AMT","value":"","placeholder":"","datatype":"numeric","restriction":"lte"},{"id":"prreceiptDtSearchId","type":"datepicker","label":"RECEIPT DATE >=","name":"pr.RECEIPT_DT","value":"","placeholder":"","datatype":"date","restriction":"gte","useDefVal":false},{"id":"prreceiptDtSearchId","type":"datepicker","label":"RECEIPT DATE <=","name":"pr.RECEIPT_DT","value":"","placeholder":"","datatype":"date","restriction":"lte","useDefVal":false}],"headerList":[{"type":"sort","label":"PDC RECEIPT NO","position":"center","name":"pr.RECEIPT_NO"},{"type":"sort","label":"RECEIPT DATE","position":"center","name":"pr.RECEIPT_DT"},{"type":"sort","label":"PDC COUNT","position":"center","name":"pr.PDC_COUNT"},{"type":"sort","label":"TOTAL PDC AMOUNT","position":"center","name":"pr.TOTAL_PDC_GROUP_AMT"},{"type":"sort","label":"RECEIVE FROM","position":"center","name":"pr.RCV_FROM_USERNAME"},{"type":"sort","label":"RECEIPT FORM NO","position":"center","name":"pr.RECEIPT_FORM_NO"}],"bodyList":[{"type":"link","position":"center","property":"PdcReceiptNo","target":"_blank","path":"/pdcreceiveview/view","param":[{"type":"PdcReceiptNo","property":"PdcReceiptNo"}]},{"type":"date","position":"center","property":"ReceiptDt"},{"type":"text","position":"center","property":"PdcCount"},{"type":"decimal","position":"right","property":"TotalPdcAmt","precision":"0.2","IsPrcnt":false},{"type":"text","position":"center","property":"ReceiveFrom"},{"type":"text","position":"center","property":"ReceiptForm"}]},"criteria":[],"whereValue":[],"fromValue":[],"useIntegration":false,"isHideSearch":false,"isSearched":false,"delay":1},"id":"871225a8-dc12-40ee-8fdd-b975e2bb5971"}],"serviceUrl":{"add":{"environment":"","apiPath":"","apiUrl":""},"edit":{"environment":"","apiPath":"","apiUrl":""},"createRfa":{"environment":"","apiPath":"","apiUrl":""}},"isRedirect":false,"redirectOption":"","redirectLink":"","hideSubmitButton":false,"listBtn":[],"customToastrMsg":"","onInit":[]}