{"title":"RECEIPT FORM REGISTRATION","id":"ReceiptFormRegistration","addButton":false,"addLink":"","pathOption":"","backButton":false,"component":[{"form":{"subsection":{"title":" RECEIPT FORM REGISTRATION","isVertical":false,"isSubsection":true,"formInput":[{"Type":"LABEL","Label":"Received Date","Variable":"FormattedBusinessDt"},{"Type":"LOOKUP","Label":"Received From","Variable":"ReceiveFromEmpNo","IsRequired":true,"IsCallback":false,"IsReadonly":true,"IsHide":false,"LookupName":"${Lookupemployeeexcluderole}","Criteria":[]},{"Type":"TEXT","Label":"Receipt Form Begin No","Variable":"BeginNo","Pattern":"","IsRequired":true,"IsUppercase":true,"IsCallback":false,"IsReadonly":false,"IsHide":false,"IsEditable":true,"Placeholder":""},{"Type":"NUMERIC","Label":"Number of Receipt Form","Variable":"NumOfReceiptForm","IsRequired":true,"IsCallback":false,"IsReadonly":false,"IsHide":false,"IsEditable":true,"Min":"0","Max":""},{"Type":"DDL","Label":"Type","Variable":"ReceiptFormType","IsRequired":true,"IsCallback":false,"IsReadonly":false,"IsHide":false,"IsEditable":true,"UseDefaultValue":false,"isUseAPI":true,"DdlItemsObj":null,"DdlReqObj":{"Environment":"FOU","Url":"/v1/RefMaster/GetListKeyValueActiveByCode","CustomObjName":"ReturnObject","CustomKeyName":"Key","CustomValueName":"Value","ReqObj":{"RefMasterTypeCode":"RECEIPT_FORM_TYPE"}}}],"onLoad":[{"environment":"PaymentUrl","apiPath":"/v1/Generic/GetFormattedBusinessDate","reqObj":[]}],"criteria":[],"isModeAdd":false}},"id":"e662334b-3f7a-4e68-9196-164cdb57f023"}],"serviceUrl":{"add":{"environment":"","apiPath":"","apiUrl":""},"detail":{"environment":"PaymentUrl","apiPath":"/v1/Generic/GetFormattedBusinessDate","apiUrl":""},"edit":{"environment":"PaymentUrl","apiPath":"/v1/ReceiptFormRegistration/SubmitReceiptFormRegistration","apiUrl":""},"createRfa":{"environment":"","apiPath":"","apiUrl":""}},"hideTitle":true,"isRedirect":true,"redirectOption":"selfPage","redirectLink":"","hideSubmitButton":false,"customToastrMsg":""}