{"lookupId":"Lookupsurveyorforsurveytask","title":"lookupSurveyorForSurveyTask","component":[{"id":"reempNameSearchId","type":"textbox","label":"Surveyor Name","name":"RE.EMP_NAME","value":"","placeholder":"","datatype":"text"},{"id":"reempNoSearchId","type":"textbox","label":"Surveyor No","name":"RE.EMP_NO","value":"","placeholder":"","datatype":"text"}],"querystring":{"name":"lookupSurveyorForSurveyTask"},"orderby":null,"headerList":[{"type":"sort","label":"Surveyor Name","position":"left","name":"RE.EMP_NAME"},{"type":"sort","label":"Surveyor No","position":"left","name":"RE.EMP_NO"},{"type":"label","position":"center","label":"Select"}],"bodyList":[{"type":"text","position":"left","property":"SurveyorName"},{"type":"text","position":"left","property":"EmployeeNo"},{"type":"action","position":"center","action":[{"type":"select","property":"SurveyorName"}]}],"propertyId":"RefUserId","propertyName":"SurveyorName","environment":"FoundationR3Url","apiVersion":"v1"}