{
  "AMENDMENTUrl": "http://idjkakb-paa1/api/amendment",
  "AMSR3AssetUrl": "http://idjkakb-paa1/api/asset",
  "AMSUrl": "http://idjkakb-paa1/api/ams",
  "APR3Url": "http://idjkakb-paa1/api/ap",
  "APR3Web": "http://idjkakb-paa1/ap",
  "ARMNTUrl": "http://idjkakb-paa1/api/armnt/",
  "ARUrl": "http://idjkakb-paa1/api/ar",
  "AmendmentUrl": "http://idjkakb-paa1/api/amendment",
  "ApprovalR3OplUrl": "http://idjkakb-paa1/api/approval/",
  "ApprovalR3OplUrlIP": "http://approval-be/",
  "ApprovalR3Url": "http://idjkakb-paa1/api/approval",
  "ApprovalR3Url_svc": "http://approval-be",
  "ApprovalURL": "http://idjkakb-paa1/api/approval",
  "AssetR3Url": "http://idjkakb-paa1/api/asset",
  "CWRR3Web": "http://idjkakb-paa1/mou",
  "CashBankR3Url": "http://idjkakb-paa1/api/cashbank",
  "CashBankUrl": "http://idjkakb-paa1/api/cashbank",
  "CashbankUrl": "http://idjkakb-paa1/api/cashbank",
  "CdeUrl": "http://r3app-server.ad-ins.com/CDE_WEB_SIT",
  "CwrURL": "http://idjkakb-paa1/api/mou",
  "DMSApiUrl": "http://kfx-svr/LITEDMS_POC/LiteDMS/pageconfins.aspx",
  "DMSUrl": "http://sky.ad-ins.com/LITEDMS_csul/Integration/ViewDoc.aspx",
  "DashboardURL": "http://r3impl-appsvr.ad-ins.com/Dashboard",
  "FMSUrl": "http://idjkakb-paa1/api/finops",
  "FilingR3Url": "http://idjkakb-paa1/api/filing",
  "FinopsR3Url": "http://idjkakb-paa1/api/finops",
  "FinopsUrl": "http://idjkakb-paa1/api/finops",
  "FoundationR3Url": "http://localhost:5000",
  "FoundationR3Url_SC": "http://192.168.1.147/CNAF_FOUNDATION_SELF_CUSTOM",
  "FoundationR3Url_svc": "http://fou-be",
  "FoundationR3Web": "http://localhost:4200",
  "GVRMNTRGLTIONR3Web": "http://idjkakb-paa1/goveregulation",
  "GVRMNTRGLTIONUrl": "http://idjkakb-paa1/api/govregulation",
  "InsuranceR3Url": "http://idjkakb-paa1/api/insurance",
  "IntegrationR3Url": "http://idjkakb-paa1/api/integration",
  "IseUseNotification": "0",
  "LMSUrl": "http://idjkakb-paa1/api/lms",
  "LocalAMENDMENTUrl": "http://idjkakb-paa1/api/amendment",
  "LocalARMNTUrl": "http://idjkakb-paa1/api/armnt",
  "LocalARUrl": "http://idjkakb-paa1/api/armnt",
  "LocalFinopsUrl": "http://idjkakb-paa1/api/finops",
  "LocalFouR3Url": "http://idjkakb-paa1/api/fou",
  "LocalPDCUrl": "http://idjkakb-paa1/api/pdc",
  "LocalPaymentUrl": "http://172.16.6.78/INTEGRATION_CNAF",
  "Localhost": "http://localhost:5002",
  "LosURL": "http://idjkakb-paa1/api/los",
  "MOUR3Web": "http://idjkakb-paa1/mou",
  "MouR3Web": "http://idjkakb-paa1/mou",
  "MouURL": "http://idjkakb-paa1/api/mou",
  "MouUrl": "http://idjkakb-paa1/api/mou",
  "NotifEngineURL": "http://idjkakb-paa1/api/notification",
  "NotificationUrl": "http://idjkakb-paa1/api/notification",
  "PDCUrl": "http://r3app-server.ad-ins.com/PDC",
  "PagesURL": "http://rnd-server-2.ad-ins.com:88/",
  "PayOutWeb": "http://idjkakb-paa1/payout",
  "PaymentUrl": "http://172.16.6.78/INTEGRATION_CNAF",
  "StorageR3Url": "http://idjkakb-paa1/api/storage",
  "Superset": "http://linuxdev4:8091/",
  "TaxR3Url": "http://idjkakb-paa1/api/tax",
  "TaxUrl": "http://idjkakb-paa1/api/tax",
  "WFThingsToDoUrl": "http://idjkakb-paa1/",
  "WebSocketURL": "http://idjkakb-paa1/api/fou/",
  "WfR3Url": "http://idjkakb-paa1/",
  "WorkflowR3Url": "http://idjkakb-paa1/camunda/",
  "WorkflowR3UrlIP": "http://idjkakb-paa1/camunda/",
  "amendmentR3Web": "http://idjkakb-paa1/amendment",
  "amsR3Url": "http://idjkakb-paa1/api/asset",
  "amsR3Web": "http://r3web-server.ad-ins.com/AMS",
  "apR3Web": "http://idjkakb-paa1/ap",
  "arR3Url": "http://idjkakb-paa1/api/ar",
  "arR3Web": "http://idjkakb-paa1/fou/notfound",
  "armntR3Web": "http://idjkakb-paa1/armnt",
  "asDocR3Url": "http://idjkakb-paa1/api/assetdoc",
  "assetPricingR3Url": "http://idjkakb-paa1/api/assetpricing",
  "assetR3Web": "http://idjkakb-paa1/asset",
  "assetdocR3Web": "http://idjkakb-paa1/assetdoc",
  "assetpricingR3Web": "http://idjkakb-paa1/assetPRICING",
  "cashbankR3Web": "http://idjkakb-paa1/cashbank",
  "cmsR3Web": "http://r3web-server.ad-ins.com/CMS_DEV",
  "contractDocR3Url": "http://idjkakb-paa1/api/agrdoc",
  "contractDocR3Web": "http://idjkakb-paa1/agrdoc",
  "creditInsR3Web": "http://idjkakb-paa1/creditins",
  "creditInsUrl": "http://idjkakb-paa1/api/creditins",
  "creditInsWeb": "http://idjkakb-paa1/creditins",
  "cwrR3Web": "http://idjkakb-paa1/mou",
  "dmsURL": "http://kfx-svr/LITEDMS_OPL/LiteDMS/pageconfins.aspx",
  "factoringUrl": "http://idjkakb-paa1/api/los",
  "filingR3Web": "http://idjkakb-paa1/filing",
  "finopsR3Web": "http://idjkakb-paa1/finops",
  "finopsUrl": "http://idjkakb-paa1/FINOPS",
  "fouR3Url": "http://idjkakb-paa1/api/fou",
  "fouR3UrlIP": "http://fou-be",
  "fouR3Urllocalhost": "http://idjkakb-paa1/api/fou",
  "fouR3Web": "http://idjkakb-paa1/fou",
  "fouR3WebMfe": "http://idjkakb-paa1/fou",
  "gvrmntrgltionR3Web": "http://idjkakb-paa1/goveregulation",
  "insuranceR3Web": "http://idjkakb-paa1/insurance",
  "integrationR3Web": "http://idjkakb-paa1/INTEGRATION",
  "lmsR3Url": "http://idjkakb-paa1/AR",
  "lmsR3Web": "http://idjkakb-paa1/fou/notfound",
  "lmsR3web": "http://idjkakb-paa1/fou/notfound",
  "lmsWeb": "http://r3impl-websvr.ad-ins.com/LMS",
  "lmsamendmentr3web": "http://idjkakb-paa1/amendment",
  "lmsarr3web": "http://idjkakb-paa1/ar",
  "lmspdc3web": "http://r3web-server.ad-ins.com/LMSPDC",
  "losR3Url": "http://idjkakb-paa1/api/los/",
  "losR3Web": "http://idjkakb-paa1/fou/notfound",
  "losUrl": "http://idjkakb-paa1/api/los",
  "paymentR3Web": "http://idjkakb-paa1/payment",
  "pdcR3Web": "http://idjkakb-paa1/pdc",
  "storageR3Web": "http://idjkakb-paa1/storage",
  "FacilityExecUrl": "http://idjkakb-paa1/api/facilityexec",
  "FacilityMntUrl": "http://idjkakb-paa1/api/facilitymnt",
  "PayOutUrl": "http://idjkakb-paa1/api/payout",
  "FacilityMntWeb": "http://idjkakb-paa1/facilitymnt",
  "FacilityExecWeb": "http://idjkakb-paa1/facilityexec"
}